{"Standings": [{"PointsDifference": 97, "Scored": 138, "Lost": 1, "Played": 5, "Team": "Ballyboden St Endas 3", "Drew": 0, "Points": 8, "Won": 4, "Competition": "U12 Hurling D Blitz Gp.2", "Conceded": 41}, {"PointsDifference": 56, "Scored": 104, "Lost": 1, "Played": 5, "Team": "Beann Eadair", "Drew": 0, "Points": 8, "Won": 4, "Competition": "U12 Hurling D Blitz Gp.2", "Conceded": 48}, {"PointsDifference": 32, "Scored": 87, "Lost": 2, "Played": 5, "Team": "St Maurs", "Drew": 0, "Points": 6, "Won": 3, "Competition": "U12 Hurling D Blitz Gp.2", "Conceded": 55}, {"PointsDifference": -61, "Scored": 22, "Lost": 3, "Played": 5, "Team": "Round Towers (C) 2", "Drew": 1, "Points": 3, "Won": 1, "Competition": "U12 Hurling D Blitz Gp.2", "Conceded": 83}, {"PointsDifference": -99, "Scored": 8, "Lost": 3, "Played": 5, "Team": "Naomh Barrog 2", "Drew": 1, "Points": 3, "Won": 1, "Competition": "U12 Hurling D Blitz Gp.2", "Conceded": 107}, {"PointsDifference": -25, "Scored": 41, "Lost": 4, "Played": 5, "Team": "Scoil Ui Chonaill", "Drew": 0, "Points": 2, "Won": 1, "Competition": "U12 Hurling D Blitz Gp.2", "Conceded": 66}], "Fixtures": [], "Results": [{"Comment": null, "HomeScore": "W/O", "Referee": "Ref: Raheny", "Grade": "Club", "AwayScore": "W/O", "HomeTeam": "Naomh Barrog 2", "Venue": "St Annes 12", "Competition": "U12 Hurling D Blitz Gp.2", "Status": "Result", "County": "Dublin", "AwayTeam": "Scoil Ui Chonaill", "CompetitionType": "Group", "Time": "12:15", "Date": "21 Apr", "Path": "Club/Dublin/Juvenile Hurling/Group", "Sport": "Juvenile Hurling"}, {"Comment": null, "HomeScore": "W-W", "Referee": "Ref: Thomas Davis", "Grade": "Club", "AwayScore": "L-L", "HomeTeam": "Ballyboden St Endas 3", "Venue": "Ballycullen", "Competition": "U12 Hurling D Blitz Gp.2", "Status": "Result", "County": "Dublin", "AwayTeam": "Beann Eadair", "CompetitionType": "Group", "Time": "12:15", "Date": "21 Apr", "Path": "Club/Dublin/Juvenile Hurling/Group", "Sport": "Juvenile Hurling"}, {"Comment": null, "HomeScore": "W-W", "Referee": "Ref: O Dwyers", "Grade": "Club", "AwayScore": "L-L", "HomeTeam": "St Maurs", "Venue": "Rush", "Competition": "U12 Hurling D Blitz Gp.2", "Status": "Result", "County": "Dublin", "AwayTeam": "Round Towers C 2", "CompetitionType": "Group", "Time": "12:15", "Date": "21 Apr", "Path": "Club/Dublin/Juvenile Hurling/Group", "Sport": "Juvenile Hurling"}, {"Comment": null, "HomeScore": "W-W", "Referee": "Ref: Scoil Ui Chonaill", "Grade": "Club", "AwayScore": "L-L", "HomeTeam": "Beann Eadair", "Venue": "Balkhill Road-Howth", "Competition": "U12 Hurling D Blitz Gp.2", "Status": "Result", "County": "Dublin", "AwayTeam": "St Maurs", "CompetitionType": "Group", "Time": "12:15", "Date": "14 Apr", "Path": "Club/Dublin/Juvenile Hurling/Group", "Sport": "Juvenile Hurling"}, {"Comment": null, "HomeScore": "W-W", "Referee": "Ref: St Vincents", "Grade": "Club", "AwayScore": "L-L", "HomeTeam": "Scoil Ui Chonaill", "Venue": "Clontarf Road", "Competition": "U12 Hurling D Blitz Gp.2", "Status": "Result", "County": "Dublin", "AwayTeam": "Ballyboden St Endas 3", "CompetitionType": "Group", "Time": "12:15", "Date": "14 Apr", "Path": "Club/Dublin/Juvenile Hurling/Group", "Sport": "Juvenile Hurling"}, {"Comment": null, "HomeScore": "D-D", "Referee": "Ref: St Marys S", "Grade": "Club", "AwayScore": "D-D", "HomeTeam": "Round Towers C 2", "Venue": "Gaelscoil Cluain Dolcain", "Competition": "U12 Hurling D Blitz Gp.2", "Status": "Result", "County": "Dublin", "AwayTeam": "Naomh Barrog 2", "CompetitionType": "Group", "Time": "12:15", "Date": "14 Apr", "Path": "Club/Dublin/Juvenile Hurling/Group", "Sport": "Juvenile Hurling"}, {"Comment": null, "HomeScore": "L-L", "Referee": "Clubs Sourcing", "Grade": "Club", "AwayScore": "W-W", "HomeTeam": "St Maurs", "Venue": "Rush", "Competition": "U12 Hurling D Blitz Gp.2", "Status": "Result", "County": "Dublin", "AwayTeam": "Ballyboden St Endas 3", "CompetitionType": "Group", "Time": "19:15", "Date": "12 Apr", "Path": "Club/Dublin/Juvenile Hurling/Group", "Sport": "Juvenile Hurling"}, {"Comment": null, "HomeScore": "W-W", "Referee": "Ref: Round Towers L", "Grade": "Club", "AwayScore": "L-L", "HomeTeam": "St Maurs", "Venue": "Rush", "Competition": "U12 Hurling D Blitz Gp.2", "Status": "Result", "County": "Dublin", "AwayTeam": "Naomh Barrog 2", "CompetitionType": "Group", "Time": "12:15", "Date": "24 Mar", "Path": "Club/Dublin/Juvenile Hurling/Group", "Sport": "Juvenile Hurling"}, {"Comment": null, "HomeScore": "L-L", "Referee": "Ref: St Vincents", "Grade": "Club", "AwayScore": "W-W", "HomeTeam": "Scoil Ui Chonaill", "Venue": "Clontarf Road", "Competition": "U12 Hurling D Blitz Gp.2", "Status": "Result", "County": "Dublin", "AwayTeam": "Beann Eadair", "CompetitionType": "Group", "Time": "12:15", "Date": "24 Mar", "Path": "Club/Dublin/Juvenile Hurling/Group", "Sport": "Juvenile Hurling"}, {"Comment": null, "HomeScore": "W-W", "Referee": "Ref: Thomas Davis", "Grade": "Club", "AwayScore": "L-L", "HomeTeam": "Ballyboden St Endas 3", "Venue": "Ballycullen", "Competition": "U12 Hurling D Blitz Gp.2", "Status": "Result", "County": "Dublin", "AwayTeam": "Round Towers C 2", "CompetitionType": "Group", "Time": "12:15", "Date": "24 Mar", "Path": "Club/Dublin/Juvenile Hurling/Group", "Sport": "Juvenile Hurling"}, {"Comment": null, "HomeScore": "W/O", "Referee": "Ref: Lucan Sarsfields", "Grade": "Club", "AwayScore": "W/O", "HomeTeam": "Round Towers C 2", "Venue": "Gaelscoil Cluain Dolcain", "Competition": "U12 Hurling D Blitz Gp.2", "Status": "Result", "County": "Dublin", "AwayTeam": "Scoil Ui Chonaill", "CompetitionType": "Group", "Time": "12:15", "Date": "10 Mar", "Path": "Club/Dublin/Juvenile Hurling/Group", "Sport": "Juvenile Hurling"}, {"Comment": null, "HomeScore": "L-L", "Referee": "Ref: Scoil Ui Chonaill", "Grade": "Club", "AwayScore": "W-W", "HomeTeam": "Naomh Barrog 2", "Venue": "St Annes 12", "Competition": "U12 Hurling D Blitz Gp.2", "Status": "Result", "County": "Dublin", "AwayTeam": "Beann Eadair", "CompetitionType": "Group", "Time": "12:15", "Date": "10 Mar", "Path": "Club/Dublin/Juvenile Hurling/Group", "Sport": "Juvenile Hurling"}, {"Comment": null, "HomeScore": "L-L", "Referee": "Ref: St Vincents", "Grade": "Club", "AwayScore": "W-W", "HomeTeam": "Scoil Ui Chonaill", "Venue": "Clontarf Road", "Competition": "U12 Hurling D Blitz Gp.2", "Status": "Result", "County": "Dublin", "AwayTeam": "St Maurs", "CompetitionType": "Group", "Time": "12:15", "Date": "24 Feb", "Path": "Club/Dublin/Juvenile Hurling/Group", "Sport": "Juvenile Hurling"}, {"Comment": null, "HomeScore": "W-W", "Referee": "Ref: St Judes", "Grade": "Club", "AwayScore": "L-L", "HomeTeam": "Ballyboden St Endas 3", "Venue": "Ballycullen", "Competition": "U12 Hurling D Blitz Gp.2", "Status": "Result", "County": "Dublin", "AwayTeam": "Naomh Barrog 2", "CompetitionType": "Group", "Time": "12:15", "Date": "24 Feb", "Path": "Club/Dublin/Juvenile Hurling/Group", "Sport": "Juvenile Hurling"}, {"Comment": null, "HomeScore": "W-W", "Referee": "Ref: Scoil Ui Chonaill", "Grade": "Club", "AwayScore": "L-L", "HomeTeam": "Beann Eadair", "Venue": "Balkhill Road-Howth", "Competition": "U12 Hurling D Blitz Gp.2", "Status": "Result", "County": "Dublin", "AwayTeam": "Round Towers C 2", "CompetitionType": "Group", "Time": "12:15", "Date": "24 Feb", "Path": "Club/Dublin/Juvenile Hurling/Group", "Sport": "Juvenile Hurling"}]}