{"Standings": [], "Fixtures": [], "Results": [{"Comment": " COMMENT: ", "HomeScore": "3-12", "Referee": "REFEREE: Kevin O Brien ", "Grade": "Club", "AwayScore": "2-15", "HomeTeam": "St Patrick's", "Venue": "Rhebogue", "Competition": "City Intermediate Hurling Championship 2018 ", "Status": "Result", "County": "Limerick", "AwayTeam": "Mungret St Pauls", "CompetitionType": "Championship", "Time": "8 00 PM", "Date": "Thursday 28 June 2018", "Path": "Club/Limerick/Men's Hurling/Championship", "Sport": "Men's Hurling"}, {"Comment": " COMMENT: ", "HomeScore": "0-4", "Referee": "REFEREE: Michael Mann ", "Grade": "Club", "AwayScore": "1-17", "HomeTeam": "Claughaun/Old Christians", "Venue": "Ballybrown", "Competition": "City Intermediate Hurling Championship 2018 ", "Status": "Result", "County": "Limerick", "AwayTeam": "Kildimo/Pallaskenry", "CompetitionType": "Championship", "Time": "7 30 PM", "Date": "Wednesday 11 July 2018", "Path": "Club/Limerick/Men's Hurling/Championship", "Sport": "Men's Hurling"}, {"Comment": " COMMENT: ", "HomeScore": "0-0", "Referee": "REFEREE: Trevor Mann ", "Grade": "Club", "AwayScore": "0-0", "HomeTeam": "Mungret St Pauls", "Venue": "Mungret St Pauls GAA", "Competition": "City Intermediate Hurling Championship 2018 ", "Status": "Result", "County": "Limerick", "AwayTeam": "St Patrick's", "CompetitionType": "Championship", "Time": "7 45 PM", "Date": "Tuesday 24 July 2018", "Path": "Club/Limerick/Men's Hurling/Championship", "Sport": "Men's Hurling"}]}