{"Standings": [], "Fixtures": [], "Results": [{"Comment": " COMMENT: ", "HomeScore": "1-13", "Referee": "REFEREE: Richard Moloney ", "Grade": "Club", "AwayScore": "3-17", "HomeTeam": "Monaleen/M\u00f3in a L\u00edn", "Venue": "Monaleen", "Competition": "City South MHC Group 2 ", "Status": "Result", "County": "Limerick", "AwayTeam": "Ballybrown GAA CLG", "CompetitionType": "Group", "Time": "7 00 PM", "Date": "Tuesday 17 April 2018", "Path": "Club/Limerick//Group", "Sport": ""}, {"Comment": " COMMENT: ", "HomeScore": "2-5", "Referee": "REFEREE: Richard Moloney ", "Grade": "Club", "AwayScore": "3-16", "HomeTeam": "Croom", "Venue": "Croom", "Competition": "City South MHC Group 2 ", "Status": "Result", "County": "Limerick", "AwayTeam": "Monaleen/M\u00f3in a L\u00edn", "CompetitionType": "Group", "Time": "7 00 PM", "Date": "Tuesday 01 May 2018", "Path": "Club/Limerick//Group", "Sport": ""}, {"Comment": " COMMENT: ", "HomeScore": "4-18", "Referee": "REFEREE: Paddy Lyons ", "Grade": "Club", "AwayScore": "0-8", "HomeTeam": "Killacolla Gaels", "Venue": "Ballyagran", "Competition": "City South MHC Group 2 ", "Status": "Result", "County": "Limerick", "AwayTeam": "Croom", "CompetitionType": "Group", "Time": "7 30 PM", "Date": "Thursday 12 July 2018", "Path": "Club/Limerick//Group", "Sport": ""}, {"Comment": " COMMENT: ", "HomeScore": "2-12", "Referee": "REFEREE: John Scully ", "Grade": "Club", "AwayScore": "3-16", "HomeTeam": "Gleann Rua CLG", "Venue": "Glenroe", "Competition": "City South MHC Group 2 ", "Status": "Result", "County": "Limerick", "AwayTeam": "Monaleen/M\u00f3in a L\u00edn", "CompetitionType": "Group", "Time": "7 00 PM", "Date": "Thursday 09 August 2018", "Path": "Club/Limerick//Group", "Sport": ""}, {"Comment": " COMMENT: ", "HomeScore": "0-0", "Referee": "REFEREE: Michael Woulfe ", "Grade": "Club", "AwayScore": "0-0", "HomeTeam": "Ballybrown GAA CLG", "Venue": "BALLYBROWN GAA", "Competition": "City South MHC Group 2 ", "Status": "Result", "County": "Limerick", "AwayTeam": "Croom", "CompetitionType": "Group", "Time": "7 00 PM", "Date": "Friday 10 August 2018", "Path": "Club/Limerick//Group", "Sport": ""}, {"Comment": " COMMENT: ", "HomeScore": "1-10", "Referee": "REFEREE: John Paul Kiely ", "Grade": "Club", "AwayScore": "3-28", "HomeTeam": "Gleann Rua CLG", "Venue": "Glenroe", "Competition": "City South MHC Group 2 ", "Status": "Result", "County": "Limerick", "AwayTeam": "Ballybrown GAA CLG", "CompetitionType": "Group", "Time": "7 00 PM", "Date": "Tuesday 14 August 2018", "Path": "Club/Limerick//Group", "Sport": ""}, {"Comment": " COMMENT: ", "HomeScore": "3-24", "Referee": "REFEREE: Liam O Sullivan ", "Grade": "Club", "AwayScore": "2-13", "HomeTeam": "Ballybrown GAA CLG", "Venue": "Ballybrown", "Competition": "City South MHC Group 2 ", "Status": "Result", "County": "Limerick", "AwayTeam": "Killacolla Gaels", "CompetitionType": "Group", "Time": "7 00 PM", "Date": "Tuesday 21 August 2018", "Path": "Club/Limerick//Group", "Sport": ""}, {"Comment": " COMMENT: ", "HomeScore": "0-18", "Referee": "REFEREE: Michael Browne ", "Grade": "Club", "AwayScore": "2-13", "HomeTeam": "Croom", "Venue": "Croom", "Competition": "City South MHC Group 2 ", "Status": "Result", "County": "Limerick", "AwayTeam": "Gleann Rua CLG", "CompetitionType": "Group", "Time": "5 00 PM", "Date": "Sunday 26 August 2018", "Path": "Club/Limerick//Group", "Sport": ""}, {"Comment": " COMMENT: ", "HomeScore": "0-1", "Referee": "REFEREE:   ", "Grade": "Club", "AwayScore": "0-0", "HomeTeam": "Killacolla Gaels", "Venue": "Bruree", "Competition": "City South MHC Group 2 ", "Status": "Result", "County": "Limerick", "AwayTeam": "Gleann Rua CLG", "CompetitionType": "Group", "Time": "7 00 PM", "Date": "Wednesday 29 August 2018", "Path": "Club/Limerick//Group", "Sport": ""}, {"Comment": " COMMENT: ", "HomeScore": "5-24", "Referee": "REFEREE: Tadgh Cronin ", "Grade": "Club", "AwayScore": "0-8", "HomeTeam": "Monaleen/M\u00f3in a L\u00edn", "Venue": "Monaleen", "Competition": "City South MHC Group 2 ", "Status": "Result", "County": "Limerick", "AwayTeam": "Killacolla Gaels", "CompetitionType": "Group", "Time": "6 45 PM", "Date": "Friday 31 August 2018", "Path": "Club/Limerick//Group", "Sport": ""}]}