{"Standings": [], "Fixtures": [], "Results": [{"Comment": " Round 1", "HomeScore": "(---)", "Referee": "Referee: Fintan Barrett", "Grade": "Club", "AwayScore": "(---)", "HomeTeam": "Suncroft GFC", "Venue": "Suncroft GFC", "Competition": "U15 Football League Division 1", "Status": "Result", "County": "Kildare", "AwayTeam": "Newtown Gaels ", "CompetitionType": "League", "Time": " 10:30 AM", "Date": "Sunday 7th Oct 2018", "Path": "Club/Kildare//League", "Sport": ""}, {"Comment": " Round 1", "HomeScore": "(0-6)", "Referee": "Referee: Barry Moore", "Grade": "Club", "AwayScore": "(1-7)", "HomeTeam": "Athy", "Venue": "Athy", "Competition": "U15 Football League Division 1", "Status": "Result", "County": "Kildare", "AwayTeam": "Naas ", "CompetitionType": "League", "Time": " 10:30 AM", "Date": "Sunday 7th Oct 2018", "Path": "Club/Kildare//League", "Sport": ""}, {"Comment": " Round 1", "HomeScore": "(1-12)", "Referee": "Referee: Paraic Mc Givern", "Grade": "Club", "AwayScore": "(2-7)", "HomeTeam": "Moorefield", "Venue": "Moorefield", "Competition": "U15 Football League Division 1", "Status": "Result", "County": "Kildare", "AwayTeam": "Maynooth ", "CompetitionType": "League", "Time": " 10:30 AM", "Date": "Sunday 7th Oct 2018", "Path": "Club/Kildare//League", "Sport": ""}, {"Comment": " Round 1", "HomeScore": "(1-4)", "Referee": "Referee:  TBC", "Grade": "Club", "AwayScore": "(1-9)", "HomeTeam": "Celbridge", "Venue": "Celbridge", "Competition": "U15 Football League Division 1", "Status": "Result", "County": "Kildare", "AwayTeam": "Sarsfields ", "CompetitionType": "League", "Time": " 10:30 AM", "Date": "Sunday 7th Oct 2018", "Path": "Club/Kildare//League", "Sport": ""}, {"Comment": " Round 1", "HomeScore": "(2-10)", "Referee": "Referee: P.j. Cummins", "Grade": "Club", "AwayScore": "(0-11)", "HomeTeam": "Clane", "Venue": "Conneff Park", "Competition": "U15 Football League Division 1", "Status": "Result", "County": "Kildare", "AwayTeam": "Balyna ", "CompetitionType": "League", "Time": " 10:30 AM", "Date": "Sunday 7th Oct 2018", "Path": "Club/Kildare//League", "Sport": ""}, {"Comment": " Round 2", "HomeScore": "(1-7)", "Referee": "Referee: P.j. Cummins", "Grade": "Club", "AwayScore": "(5-13)", "HomeTeam": "Maynooth", "Venue": "Maynooth", "Competition": "U15 Football League Division 1", "Status": "Result", "County": "Kildare", "AwayTeam": "Suncroft GFC ", "CompetitionType": "League", "Time": " 10:30 AM", "Date": "Sunday 14th Oct 2018", "Path": "Club/Kildare//League", "Sport": ""}, {"Comment": " Round 2", "HomeScore": "(4-8)", "Referee": "Referee: Peter Farrell", "Grade": "Club", "AwayScore": "(1-12)", "HomeTeam": "Newtown Gaels", "Venue": null, "Competition": "U15 Football League Division 1", "Status": "Result", "County": "Kildare", "AwayTeam": "Athy ", "CompetitionType": "League", "Time": " 10:30 AM", "Date": "Sunday 14th Oct 2018", "Path": "Club/Kildare//League", "Sport": ""}, {"Comment": " Round 2", "HomeScore": "(3-10)", "Referee": "Referee:  TBC", "Grade": "Club", "AwayScore": "(3-10)", "HomeTeam": "Naas", "Venue": "Naas", "Competition": "U15 Football League Division 1", "Status": "Result", "County": "Kildare", "AwayTeam": "Celbridge ", "CompetitionType": "League", "Time": " 10:30 AM", "Date": "Sunday 14th Oct 2018", "Path": "Club/Kildare//League", "Sport": ""}, {"Comment": " Round 2", "HomeScore": "(1-4)", "Referee": "Referee: Paraic Mc Givern", "Grade": "Club", "AwayScore": "(2-13)", "HomeTeam": "Sarsfields", "Venue": "Sarsfields GAA Club", "Competition": "U15 Football League Division 1", "Status": "Result", "County": "Kildare", "AwayTeam": "Clane ", "CompetitionType": "League", "Time": " 10:30 AM", "Date": "Sunday 14th Oct 2018", "Path": "Club/Kildare//League", "Sport": ""}, {"Comment": " Round 2", "HomeScore": "(---)", "Referee": "Referee: Michael Behan", "Grade": "Club", "AwayScore": "(---)", "HomeTeam": "Balyna", "Venue": "Johnstownbridge", "Competition": "U15 Football League Division 1", "Status": "Result", "County": "Kildare", "AwayTeam": "Moorefield ", "CompetitionType": "League", "Time": " 7:30 PM", "Date": "Wednesday 17th Oct 2018", "Path": "Club/Kildare//League", "Sport": ""}, {"Comment": " Round 3", "HomeScore": "(5-10)", "Referee": "Referee: Stephen Foley", "Grade": "Club", "AwayScore": "(2-6)", "HomeTeam": "Athy", "Venue": "Athy", "Competition": "U15 Football League Division 1", "Status": "Result", "County": "Kildare", "AwayTeam": "Maynooth ", "CompetitionType": "League", "Time": " 10:30 AM", "Date": "Sunday 21st Oct 2018", "Path": "Club/Kildare//League", "Sport": ""}, {"Comment": " Round 3", "HomeScore": "(7-11)", "Referee": "Referee: Robert Kennedy", "Grade": "Club", "AwayScore": "(1-5)", "HomeTeam": "Suncroft GFC", "Venue": "Suncroft GFC", "Competition": "U15 Football League Division 1", "Status": "Result", "County": "Kildare", "AwayTeam": "Balyna ", "CompetitionType": "League", "Time": " 10:30 AM", "Date": "Sunday 21st Oct 2018", "Path": "Club/Kildare//League", "Sport": ""}, {"Comment": " Round 3", "HomeScore": "(3-9)", "Referee": "Referee: Eamonn Kelly", "Grade": "Club", "AwayScore": "(3-6)", "HomeTeam": "Celbridge", "Venue": "Celbridge", "Competition": "U15 Football League Division 1", "Status": "Result", "County": "Kildare", "AwayTeam": "Newtown Gaels ", "CompetitionType": "League", "Time": " 10:30 AM", "Date": "Sunday 21st Oct 2018", "Path": "Club/Kildare//League", "Sport": ""}, {"Comment": " Round 3", "HomeScore": "(3-15)", "Referee": "Referee: Craig Hughes", "Grade": "Club", "AwayScore": "(2-10)", "HomeTeam": "Clane", "Venue": "Conneff Park", "Competition": "U15 Football League Division 1", "Status": "Result", "County": "Kildare", "AwayTeam": "Moorefield ", "CompetitionType": "League", "Time": " 10:30 AM", "Date": "Sunday 21st Oct 2018", "Path": "Club/Kildare//League", "Sport": ""}, {"Comment": " Round 3", "HomeScore": "(1-12)", "Referee": "Referee: Niall Colgan", "Grade": "Club", "AwayScore": "(3-5)", "HomeTeam": "Sarsfields", "Venue": "Sarsfields GAA Club", "Competition": "U15 Football League Division 1", "Status": "Result", "County": "Kildare", "AwayTeam": "Naas ", "CompetitionType": "League", "Time": " 10:30 AM", "Date": "Sunday 21st Oct 2018", "Path": "Club/Kildare//League", "Sport": ""}, {"Comment": " Round 4", "HomeScore": "(2-9)", "Referee": "Referee:  TBC", "Grade": "Club", "AwayScore": "(1-12)", "HomeTeam": "Maynooth", "Venue": "Maynooth", "Competition": "U15 Football League Division 1", "Status": "Result", "County": "Kildare", "AwayTeam": "Celbridge ", "CompetitionType": "League", "Time": " 10:30 AM", "Date": "Sunday 28th Oct 2018", "Path": "Club/Kildare//League", "Sport": ""}, {"Comment": " Round 4", "HomeScore": "(1-8)", "Referee": "Referee: Thomas Smyth", "Grade": "Club", "AwayScore": "(1-9)", "HomeTeam": "Newtown Gaels", "Venue": null, "Competition": "U15 Football League Division 1", "Status": "Result", "County": "Kildare", "AwayTeam": "Sarsfields ", "CompetitionType": "League", "Time": " 10:30 AM", "Date": "Sunday 28th Oct 2018", "Path": "Club/Kildare//League", "Sport": ""}, {"Comment": " Round 4", "HomeScore": "(---)", "Referee": "Referee: Lee Moore", "Grade": "Club", "AwayScore": "(---)", "HomeTeam": "Moorefield", "Venue": "Moorefield", "Competition": "U15 Football League Division 1", "Status": "Result", "County": "Kildare", "AwayTeam": "Suncroft GFC ", "CompetitionType": "League", "Time": " 10:30 AM", "Date": "Sunday 28th Oct 2018", "Path": "Club/Kildare//League", "Sport": ""}, {"Comment": " Round 4", "HomeScore": "(---)", "Referee": "Referee:  TBC", "Grade": "Club", "AwayScore": "(---)", "HomeTeam": "Naas", "Venue": "Naas", "Competition": "U15 Football League Division 1", "Status": "Result", "County": "Kildare", "AwayTeam": "Clane ", "CompetitionType": "League", "Time": " 10:30 AM", "Date": "Sunday 28th Oct 2018", "Path": "Club/Kildare//League", "Sport": ""}, {"Comment": " Round 4", "HomeScore": "(2-6)", "Referee": "Referee: Damien Reilly", "Grade": "Club", "AwayScore": "(5-15)", "HomeTeam": "Balyna", "Venue": "Balyna", "Competition": "U15 Football League Division 1", "Status": "Result", "County": "Kildare", "AwayTeam": "Athy ", "CompetitionType": "League", "Time": " 10:30 AM", "Date": "Sunday 28th Oct 2018", "Path": "Club/Kildare//League", "Sport": ""}, {"Comment": " Round 5", "HomeScore": "(3-15)", "Referee": "Referee: John Knight", "Grade": "Club", "AwayScore": "(4-10)", "HomeTeam": "Athy", "Venue": "Athy", "Competition": "U15 Football League Division 1", "Status": "Result", "County": "Kildare", "AwayTeam": "Moorefield ", "CompetitionType": "League", "Time": " 6:30 PM", "Date": "Wednesday 31st Oct 2018", "Path": "Club/Kildare//League", "Sport": ""}, {"Comment": " Round 5", "HomeScore": "(8-14)", "Referee": "Referee: Owen Murphy", "Grade": "Club", "AwayScore": "(1-13)", "HomeTeam": "Naas", "Venue": "Naas", "Competition": "U15 Football League Division 1", "Status": "Result", "County": "Kildare", "AwayTeam": "Newtown Gaels ", "CompetitionType": "League", "Time": " 6:30 PM", "Date": "Wednesday 31st Oct 2018", "Path": "Club/Kildare//League", "Sport": ""}, {"Comment": " Round 5", "HomeScore": "(7-19)", "Referee": "Referee: Eamonn Kelly", "Grade": "Club", "AwayScore": "(1-13)", "HomeTeam": "Celbridge", "Venue": "Celbridge", "Competition": "U15 Football League Division 1", "Status": "Result", "County": "Kildare", "AwayTeam": "Balyna ", "CompetitionType": "League", "Time": " 6:30 PM", "Date": "Wednesday 31st Oct 2018", "Path": "Club/Kildare//League", "Sport": ""}, {"Comment": " Round 5", "HomeScore": "(2-11)", "Referee": "Referee: Michael Malone", "Grade": "Club", "AwayScore": "(4-8)", "HomeTeam": "Clane", "Venue": "Conneff Park", "Competition": "U15 Football League Division 1", "Status": "Result", "County": "Kildare", "AwayTeam": "Suncroft GFC ", "CompetitionType": "League", "Time": " 6:30 PM", "Date": "Wednesday 31st Oct 2018", "Path": "Club/Kildare//League", "Sport": ""}, {"Comment": " Round 5", "HomeScore": "(4-14)", "Referee": "Referee: David Coady", "Grade": "Club", "AwayScore": "(7-9)", "HomeTeam": "Sarsfields", "Venue": "Sarsfields GAA Club", "Competition": "U15 Football League Division 1", "Status": "Result", "County": "Kildare", "AwayTeam": "Maynooth ", "CompetitionType": "League", "Time": " 6:30 PM", "Date": "Wednesday 31st Oct 2018", "Path": "Club/Kildare//League", "Sport": ""}, {"Comment": " Round 6", "HomeScore": "(5-9)", "Referee": "Referee: Fintan Barrett", "Grade": "Club", "AwayScore": "(1-14)", "HomeTeam": "Suncroft GFC", "Venue": "Suncroft GFC", "Competition": "U15 Football League Division 1", "Status": "Result", "County": "Kildare", "AwayTeam": "Athy ", "CompetitionType": "League", "Time": " 10:30 AM", "Date": "Sunday 4th Nov 2018", "Path": "Club/Kildare//League", "Sport": ""}, {"Comment": " Round 6", "HomeScore": "(3-6)", "Referee": "Referee: Larry Heeney", "Grade": "Club", "AwayScore": "(5-8)", "HomeTeam": "Maynooth", "Venue": "Maynooth", "Competition": "U15 Football League Division 1", "Status": "Result", "County": "Kildare", "AwayTeam": "Naas ", "CompetitionType": "League", "Time": " 10:30 AM", "Date": "Sunday 4th Nov 2018", "Path": "Club/Kildare//League", "Sport": ""}, {"Comment": " Round 6", "HomeScore": "(2-14)", "Referee": "Referee: Peter Farrell", "Grade": "Club", "AwayScore": "(3-8)", "HomeTeam": "Newtown Gaels", "Venue": null, "Competition": "U15 Football League Division 1", "Status": "Result", "County": "Kildare", "AwayTeam": "Clane ", "CompetitionType": "League", "Time": " 10:30 AM", "Date": "Sunday 4th Nov 2018", "Path": "Club/Kildare//League", "Sport": ""}, {"Comment": " Round 6", "HomeScore": "(---)", "Referee": "Referee: Niall Colgan", "Grade": "Club", "AwayScore": "(---)", "HomeTeam": "Moorefield", "Venue": "Moorefield", "Competition": "U15 Football League Division 1", "Status": "Result", "County": "Kildare", "AwayTeam": "Celbridge ", "CompetitionType": "League", "Time": " 10:30 AM", "Date": "Sunday 4th Nov 2018", "Path": "Club/Kildare//League", "Sport": ""}, {"Comment": " Round 6", "HomeScore": "(5-11)", "Referee": "Referee: Damien Reilly", "Grade": "Club", "AwayScore": "(5-7)", "HomeTeam": "Balyna", "Venue": "Balyna", "Competition": "U15 Football League Division 1", "Status": "Result", "County": "Kildare", "AwayTeam": "Sarsfields ", "CompetitionType": "League", "Time": " 10:30 AM", "Date": "Sunday 4th Nov 2018", "Path": "Club/Kildare//League", "Sport": ""}, {"Comment": " Round 7", "HomeScore": "(---)", "Referee": "Referee:  TBC", "Grade": "Club", "AwayScore": "(---)", "HomeTeam": "Celbridge", "Venue": "Celbridge", "Competition": "U15 Football League Division 1", "Status": "Result", "County": "Kildare", "AwayTeam": "Suncroft GFC ", "CompetitionType": "League", "Time": " 7:30 PM", "Date": "Thursday 8th Nov 2018", "Path": "Club/Kildare//League", "Sport": ""}, {"Comment": " Round 7", "HomeScore": "(4-9)", "Referee": "Referee: Liam Herbert", "Grade": "Club", "AwayScore": "(1-11)", "HomeTeam": "Clane", "Venue": "Conneff Park", "Competition": "U15 Football League Division 1", "Status": "Result", "County": "Kildare", "AwayTeam": "Athy ", "CompetitionType": "League", "Time": " 10:30 AM", "Date": "Sunday 11th Nov 2018", "Path": "Club/Kildare//League", "Sport": ""}, {"Comment": " Round 7", "HomeScore": "(7-11)", "Referee": "Referee: Billy O Connell", "Grade": "Club", "AwayScore": "(2-9)", "HomeTeam": "Sarsfields", "Venue": "Sarsfields GAA Club", "Competition": "U15 Football League Division 1", "Status": "Result", "County": "Kildare", "AwayTeam": "Moorefield ", "CompetitionType": "League", "Time": " 10:30 AM", "Date": "Sunday 11th Nov 2018", "Path": "Club/Kildare//League", "Sport": ""}, {"Comment": " Round 7", "HomeScore": "(1-10)", "Referee": "Referee: Damien Reilly", "Grade": "Club", "AwayScore": "(4-10)", "HomeTeam": "Newtown Gaels", "Venue": null, "Competition": "U15 Football League Division 1", "Status": "Result", "County": "Kildare", "AwayTeam": "Maynooth ", "CompetitionType": "League", "Time": " 10:30 AM", "Date": "Sunday 11th Nov 2018", "Path": "Club/Kildare//League", "Sport": ""}, {"Comment": " Round 7", "HomeScore": "(1-11)", "Referee": "Referee: Larry Heeney", "Grade": "Club", "AwayScore": "(2-12)", "HomeTeam": "Naas", "Venue": "Naas", "Competition": "U15 Football League Division 1", "Status": "Result", "County": "Kildare", "AwayTeam": "Balyna ", "CompetitionType": "League", "Time": " 10:30 AM", "Date": "Sunday 11th Nov 2018", "Path": "Club/Kildare//League", "Sport": ""}, {"Comment": " Round 8", "HomeScore": "(7-15)", "Referee": "Referee: Barry Moore", "Grade": "Club", "AwayScore": "(0-9)", "HomeTeam": "Athy", "Venue": "Athy", "Competition": "U15 Football League Division 1", "Status": "Result", "County": "Kildare", "AwayTeam": "Celbridge ", "CompetitionType": "League", "Time": " 10:30 AM", "Date": "Sunday 18th Nov 2018", "Path": "Club/Kildare//League", "Sport": ""}, {"Comment": " Round 8", "HomeScore": "(---)", "Referee": "Referee: Kieran Harris", "Grade": "Club", "AwayScore": "(---)", "HomeTeam": "Suncroft GFC", "Venue": "Suncroft GFC", "Competition": "U15 Football League Division 1", "Status": "Result", "County": "Kildare", "AwayTeam": "Sarsfields ", "CompetitionType": "League", "Time": " 10:30 AM", "Date": "Sunday 18th Nov 2018", "Path": "Club/Kildare//League", "Sport": ""}, {"Comment": " Round 8", "HomeScore": "(3-7)", "Referee": "Referee: Conor Daly", "Grade": "Club", "AwayScore": "(2-9)", "HomeTeam": "Maynooth", "Venue": "Maynooth", "Competition": "U15 Football League Division 1", "Status": "Result", "County": "Kildare", "AwayTeam": "Clane ", "CompetitionType": "League", "Time": " 10:30 AM", "Date": "Sunday 18th Nov 2018", "Path": "Club/Kildare//League", "Sport": ""}, {"Comment": " Round 8", "HomeScore": "(5-14)", "Referee": "Referee: Owen Murphy", "Grade": "Club", "AwayScore": "(5-3)", "HomeTeam": "Moorefield", "Venue": "Moorefield", "Competition": "U15 Football League Division 1", "Status": "Result", "County": "Kildare", "AwayTeam": "Naas ", "CompetitionType": "League", "Time": " 10:30 AM", "Date": "Sunday 18th Nov 2018", "Path": "Club/Kildare//League", "Sport": ""}, {"Comment": " Round 8", "HomeScore": "(4-15)", "Referee": "Referee: Fergus Deveraux", "Grade": "Club", "AwayScore": "(2-8)", "HomeTeam": "Balyna", "Venue": "Balyna", "Competition": "U15 Football League Division 1", "Status": "Result", "County": "Kildare", "AwayTeam": "Newtown Gaels ", "CompetitionType": "League", "Time": " 10:30 AM", "Date": "Sunday 18th Nov 2018", "Path": "Club/Kildare//League", "Sport": ""}, {"Comment": " Round 9", "HomeScore": "(5-17)", "Referee": "Referee: Liam Herbert", "Grade": "Club", "AwayScore": "(1-5)", "HomeTeam": "Newtown Gaels", "Venue": null, "Competition": "U15 Football League Division 1", "Status": "Result", "County": "Kildare", "AwayTeam": "Moorefield ", "CompetitionType": "League", "Time": " 10:30 AM", "Date": "Sunday 25th Nov 2018", "Path": "Club/Kildare//League", "Sport": ""}, {"Comment": " Round 9", "HomeScore": "(2-7)", "Referee": "Referee: Michael Behan", "Grade": "Club", "AwayScore": "(3-12)", "HomeTeam": "Naas", "Venue": "Naas", "Competition": "U15 Football League Division 1", "Status": "Result", "County": "Kildare", "AwayTeam": "Suncroft GFC ", "CompetitionType": "League", "Time": " 10:30 AM", "Date": "Sunday 25th Nov 2018", "Path": "Club/Kildare//League", "Sport": ""}, {"Comment": " Round 9", "HomeScore": "(2-13)", "Referee": "Referee: Paraic Mc Givern", "Grade": "Club", "AwayScore": "(1-8)", "HomeTeam": "Clane", "Venue": "Conneff Park", "Competition": "U15 Football League Division 1", "Status": "Result", "County": "Kildare", "AwayTeam": "Celbridge ", "CompetitionType": "League", "Time": " 10:30 AM", "Date": "Sunday 25th Nov 2018", "Path": "Club/Kildare//League", "Sport": ""}, {"Comment": " Round 9", "HomeScore": "(0-7)", "Referee": "Referee: Niall Colgan", "Grade": "Club", "AwayScore": "(4-15)", "HomeTeam": "Sarsfields", "Venue": "Sarsfields GAA Club", "Competition": "U15 Football League Division 1", "Status": "Result", "County": "Kildare", "AwayTeam": "Athy ", "CompetitionType": "League", "Time": " 10:30 AM", "Date": "Sunday 25th Nov 2018", "Path": "Club/Kildare//League", "Sport": ""}, {"Comment": " Round 9", "HomeScore": "(5-6)", "Referee": "Referee: Larry Heeney", "Grade": "Club", "AwayScore": "(4-11)", "HomeTeam": "Maynooth", "Venue": "Maynooth", "Competition": "U15 Football League Division 1", "Status": "Result", "County": "Kildare", "AwayTeam": "Balyna ", "CompetitionType": "League", "Time": " 10:30 AM", "Date": "Sunday 25th Nov 2018", "Path": "Club/Kildare//League", "Sport": ""}, {"Comment": " play off", "HomeScore": "(2-10)", "Referee": "Referee: Owen Murphy", "Grade": "Club", "AwayScore": "(4-5)", "HomeTeam": "Sarsfields", "Venue": "Sarsfields GAA Club", "Competition": "U15 Football League Division 1", "Status": "Result", "County": "Kildare", "AwayTeam": "Maynooth ", "CompetitionType": "League", "Time": " 10:30 AM", "Date": "Sunday 2nd Dec 2018", "Path": "Club/Kildare//League", "Sport": ""}, {"Comment": " play off", "HomeScore": "(0-13)", "Referee": "Referee: Alan Archbold", "Grade": "Club", "AwayScore": "(3-16)", "HomeTeam": "Moorefield", "Venue": "Naas", "Competition": "U15 Football League Division 1", "Status": "Result", "County": "Kildare", "AwayTeam": "Balyna ", "CompetitionType": "League", "Time": " 10:30 AM", "Date": "Sunday 2nd Dec 2018", "Path": "Club/Kildare//League", "Sport": ""}, {"Comment": " Semi Final", "HomeScore": "(1-21)", "Referee": "Referee: Anthony Herbert", "Grade": "Club", "AwayScore": "(2-10)", "HomeTeam": "Clane", "Venue": "Conneff Park", "Competition": "U15 Football League Division 1", "Status": "Result", "County": "Kildare", "AwayTeam": "Athy ", "CompetitionType": "League", "Time": " 10:30 AM", "Date": "Sunday 2nd Dec 2018", "Path": "Club/Kildare//League", "Sport": ""}, {"Comment": " Semi Final", "HomeScore": "(3-10)", "Referee": "Referee: David Houlihan", "Grade": "Club", "AwayScore": "(4-11)", "HomeTeam": "Suncroft GFC", "Venue": "Manguard Plus Kildare GAA COE Hawkfield Pitch 2", "Competition": "U15 Football League Division 1", "Status": "Result", "County": "Kildare", "AwayTeam": "Balyna ", "CompetitionType": "League", "Time": " 7:30 PM", "Date": "Wednesday 5th Dec 2018", "Path": "Club/Kildare//League", "Sport": ""}, {"Comment": " Semi-Finals", "HomeScore": "(2-7)", "Referee": "Referee: Anthony Herbert", "Grade": "Club", "AwayScore": "(1-7)", "HomeTeam": "Naas", "Venue": "Naas", "Competition": "U15 Football League Division 1", "Status": "Result", "County": "Kildare", "AwayTeam": "Moorefield ", "CompetitionType": "League", "Time": " 7:30 PM", "Date": "Wednesday 5th Dec 2018", "Path": "Club/Kildare//League", "Sport": ""}, {"Comment": " Medal Final", "HomeScore": "(2-8)", "Referee": "Referee: Lee Moore", "Grade": "Club", "AwayScore": "(2-7)", "HomeTeam": "Maynooth", "Venue": "Manguard Plus Kildare GAA COE Hawkfield Pitch 2", "Competition": "U15 Football League Division 1", "Status": "Result", "County": "Kildare", "AwayTeam": "Naas ", "CompetitionType": "League", "Time": " 3:00 PM", "Date": "Saturday 8th Dec 2018", "Path": "Club/Kildare//League", "Sport": ""}, {"Comment": " Final", "HomeScore": "(---)", "Referee": "Referee:  TBC", "Grade": "Club", "AwayScore": "(---)", "HomeTeam": "Clane", "Venue": "Manguard Plus Kildare GAA COE Hawkfield Pitch 2", "Competition": "U15 Football League Division 1", "Status": "Result", "County": "Kildare", "AwayTeam": "Suncroft GFC ", "CompetitionType": "League", "Time": " 4:15 PM", "Date": "Saturday 8th Dec 2018", "Path": "Club/Kildare//League", "Sport": ""}]}