{"Standings": [], "Fixtures": [{"Comment": "", "HomeScore": "4-5", "Referee": "John Mc Mullan", "Grade": "Club", "AwayScore": "7-5", "HomeTeam": "Carryduff  ", "Venue": "Carryduff", "Competition": "East Down U13 Div 3A Championship Sponsored by Homecare Ventilation & Vacuum", "Status": "Fixture", "County": "Down", "AwayTeam": " St Paul's ", "CompetitionType": "Championship", "Time": "11 00 AM", "Date": "", "Path": "Club/Down//Championship", "Sport": ""}], "Results": [{"Comment": "", "HomeScore": "10-15", "Referee": "Liam Morgan", "Grade": "Club", "AwayScore": "3-4", "HomeTeam": "Aughlisnafin  ", "Venue": "Pairc Baile Anna, Annsborough", "Competition": "East Down U13 Div 3A Championship Sponsored by Homecare Ventilation & Vacuum", "Status": "Result", "County": "Down", "AwayTeam": " Carryduff ", "CompetitionType": "Championship", "Time": "11 00 AM", "Date": "Sunday 21st Oct 2018", "Path": "Club/Down//Championship", "Sport": ""}, {"Comment": "", "HomeScore": "2-5", "Referee": "Simon Francis", "Grade": "Club", "AwayScore": "4-5", "HomeTeam": "St Paul's  ", "Venue": "St Pauls", "Competition": "East Down U13 Div 3A Championship Sponsored by Homecare Ventilation & Vacuum", "Status": "Result", "County": "Down", "AwayTeam": " Aughlisnafin ", "CompetitionType": "Championship", "Time": "11 00 AM", "Date": "Sunday 14th Oct 2018", "Path": "Club/Down//Championship", "Sport": ""}]}