{"Standings": [], "Fixtures": [], "Results": [{"Comment": "conceded by naomh fionnbarra", "HomeScore": null, "Referee": "Peter Trimble", "Grade": "Club", "AwayScore": null, "HomeTeam": "Na Fianna B", "Venue": "Collinstown Lane", "Competition": "Under 16 Division 5 Championship Group A", "Status": "Result", "County": "Dublin", "AwayTeam": "Naomh Fionnbarra", "CompetitionType": "Championship", "Time": "10:00", "Date": "02/09/2018", "Path": "Club/Dublin/Ladies Football/Championship", "Sport": "Ladies Football"}, {"Comment": null, "HomeScore": "3-4", "Referee": "George Williams", "Grade": "Club", "AwayScore": "4-25", "HomeTeam": "St Oliver Plunketts B", "Venue": "Martin Savage Park", "Competition": "Under 16 Division 5 Championship Group A", "Status": "Result", "County": "Dublin", "AwayTeam": "Lucan Sarsfields B", "CompetitionType": "Championship", "Time": "10:00", "Date": "02/09/2018", "Path": "Club/Dublin/Ladies Football/Championship", "Sport": "Ladies Football"}, {"Comment": null, "HomeScore": "2-11", "Referee": "Suzanne Ford", "Grade": "Club", "AwayScore": "1-17", "HomeTeam": "Lucan Sarsfields B", "Venue": "12th Lock", "Competition": "Under 16 Division 5 Championship Group A", "Status": "Result", "County": "Dublin", "AwayTeam": "Na Fianna B", "CompetitionType": "Championship", "Time": "19:00", "Date": "06/09/2018", "Path": "Club/Dublin/Ladies Football/Championship", "Sport": "Ladies Football"}, {"Comment": "conceded by naomh fionnbarra", "HomeScore": null, "Referee": "George Williams", "Grade": "Club", "AwayScore": null, "HomeTeam": "Naomh Fionnbarra", "Venue": "Pope John Paul Park II", "Competition": "Under 16 Division 5 Championship Group A", "Status": "Result", "County": "Dublin", "AwayTeam": "Cuala B", "CompetitionType": "Championship", "Time": "19:00", "Date": "06/09/2018", "Path": "Club/Dublin/Ladies Football/Championship", "Sport": "Ladies Football"}, {"Comment": "conceded by naomh fionnbarra", "HomeScore": null, "Referee": "Danny Harrington", "Grade": "Club", "AwayScore": null, "HomeTeam": "Naomh Fionnbarra", "Venue": "Pope John Paul Park II", "Competition": "Under 16 Division 5 Championship Group A", "Status": "Result", "County": "Dublin", "AwayTeam": "Lucan Sarsfields B", "CompetitionType": "Championship", "Time": "16:30", "Date": "09/09/2018", "Path": "Club/Dublin/Ladies Football/Championship", "Sport": "Ladies Football"}, {"Comment": "conceded by cuala b", "HomeScore": null, "Referee": "Reg Harbron", "Grade": "Club", "AwayScore": null, "HomeTeam": "Cuala B", "Venue": "Martin Savage Park", "Competition": "Under 16 Division 5 Championship Group A", "Status": "Result", "County": "Dublin", "AwayTeam": "St Oliver Plunketts B", "CompetitionType": "Championship", "Time": "18:45", "Date": "10/09/2018", "Path": "Club/Dublin/Ladies Football/Championship", "Sport": "Ladies Football"}, {"Comment": null, "HomeScore": "4-10", "Referee": "Laura Bourke", "Grade": "Club", "AwayScore": "8-2", "HomeTeam": "Lucan Sarsfields B", "Venue": "12th Lock", "Competition": "Under 16 Division 5 Championship Group A", "Status": "Result", "County": "Dublin", "AwayTeam": "Cuala B", "CompetitionType": "Championship", "Time": "16:30", "Date": "23/09/2018", "Path": "Club/Dublin/Ladies Football/Championship", "Sport": "Ladies Football"}, {"Comment": null, "HomeScore": "14-17", "Referee": "Lisa Brett", "Grade": "Club", "AwayScore": "3-2", "HomeTeam": "Na Fianna B", "Venue": "Collinstown Lane", "Competition": "Under 16 Division 5 Championship Group A", "Status": "Result", "County": "Dublin", "AwayTeam": "St Oliver Plunketts B", "CompetitionType": "Championship", "Time": "16:30", "Date": "23/09/2018", "Path": "Club/Dublin/Ladies Football/Championship", "Sport": "Ladies Football"}, {"Comment": "exact score to follow", "HomeScore": "0-1", "Referee": "John Doherty", "Grade": "Club", "AwayScore": "0-0", "HomeTeam": "Cuala B", "Venue": "Meadowvale", "Competition": "Under 16 Division 5 Championship Group A", "Status": "Result", "County": "Dublin", "AwayTeam": "Na Fianna B", "CompetitionType": "Championship", "Time": "16:30", "Date": "30/09/2018", "Path": "Club/Dublin/Ladies Football/Championship", "Sport": "Ladies Football"}, {"Comment": "conceded by naomh fionnbarra", "HomeScore": null, "Referee": "Gerry McNally", "Grade": "Club", "AwayScore": null, "HomeTeam": "St Oliver Plunketts B", "Venue": "Martin Savage Park", "Competition": "Under 16 Division 5 Championship Group A", "Status": "Result", "County": "Dublin", "AwayTeam": "Naomh Fionnbarra", "CompetitionType": "Championship", "Time": "16:30", "Date": "30/09/2018", "Path": "Club/Dublin/Ladies Football/Championship", "Sport": "Ladies Football"}]}