{"Standings": [], "Fixtures": [], "Results": [{"Comment": " COMMENT: ", "HomeScore": "3-7", "Referee": "REFEREE: Niall Cullen ", "Grade": "Club", "AwayScore": "5-19", "HomeTeam": "Limerick", "Venue": "Gaelic Grounds, Limerick", "Competition": "GAA Football All-Ireland Senior Championship", "Status": "Result", "County": "Limerick", "AwayTeam": "Mayo", "CompetitionType": "Championship", "Time": "6 00 PM", "Date": "Saturday 09 June 2018", "Path": "Club/Limerick/Men's Football/Championship", "Sport": "Men's Football"}]}