{"Standings": [{"PointsDifference": 24, "Scored": 56, "Lost": 1, "Played": 3, "Team": "Na Gaeil Oga", "Drew": 0, "Points": 4, "Won": 2, "Competition": "Junior 1 Football Club Championship Group Three", "Conceded": 32}, {"PointsDifference": 20, "Scored": 34, "Lost": 0, "Played": 2, "Team": "Man O War", "Drew": 0, "Points": 4, "Won": 2, "Competition": "Junior 1 Football Club Championship Group Three", "Conceded": 14}, {"PointsDifference": -17, "Scored": 34, "Lost": 2, "Played": 3, "Team": "St Kevin-Killians", "Drew": 0, "Points": 2, "Won": 1, "Competition": "Junior 1 Football Club Championship Group Three", "Conceded": 51}, {"PointsDifference": -27, "Scored": 18, "Lost": 2, "Played": 2, "Team": "Civil Service Football", "Drew": 0, "Points": 0, "Won": 0, "Competition": "Junior 1 Football Club Championship Group Three", "Conceded": 45}], "Fixtures": [], "Results": [{"Comment": null, "HomeScore": "9-14", "Referee": "Gary Carthy", "Grade": "Club", "AwayScore": "0-8", "HomeTeam": "Man O War", "Venue": "Man O War", "Competition": "Junior 1 Football Club Championship Group Three", "Status": "Result", "County": "Dublin", "AwayTeam": "Civil Service Football", "CompetitionType": "Championship", "Time": "11:00", "Date": "16 Sep", "Path": "Club/Dublin//Championship", "Sport": ""}, {"Comment": null, "HomeScore": "2-17", "Referee": "Robbie Glennon", "Grade": "Club", "AwayScore": "1-5", "HomeTeam": "Na Gaeil Oga", "Venue": "St Catherines Park", "Competition": "Junior 1 Football Club Championship Group Three", "Status": "Result", "County": "Dublin", "AwayTeam": "St Kevins Killians", "CompetitionType": "Championship", "Time": "11:00", "Date": "16 Sep", "Path": "Club/Dublin//Championship", "Sport": ""}, {"Comment": null, "HomeScore": "2-11", "Referee": "Ian Howley", "Grade": "Club", "AwayScore": "0-4", "HomeTeam": "Man O War", "Venue": "Man O War", "Competition": "Junior 1 Football Club Championship Group Three", "Status": "Result", "County": "Dublin", "AwayTeam": "St Kevins Killians", "CompetitionType": "Championship", "Time": "11:00", "Date": "29 Apr", "Path": "Club/Dublin//Championship", "Sport": ""}, {"Comment": null, "HomeScore": "0-7", "Referee": "John Durkan", "Grade": "Club", "AwayScore": "4-11", "HomeTeam": "Civil Service Football", "Venue": "Islandbridge", "Competition": "Junior 1 Football Club Championship Group Three", "Status": "Result", "County": "Dublin", "AwayTeam": "Na Gaeil Oga", "CompetitionType": "Championship", "Time": "11:00", "Date": "29 Apr", "Path": "Club/Dublin//Championship", "Sport": ""}, {"Comment": null, "HomeScore": "5-7", "Referee": "John Durkan", "Grade": "Club", "AwayScore": "3-2", "HomeTeam": "St Kevins Killians", "Venue": "Kingswood", "Competition": "Junior 1 Football Club Championship Group Three", "Status": "Result", "County": "Dublin", "AwayTeam": "Civil Service Football", "CompetitionType": "Championship", "Time": "11:00", "Date": "15 Apr", "Path": "Club/Dublin//Championship", "Sport": ""}, {"Comment": null, "HomeScore": "1-7", "Referee": "John Doherty", "Grade": "Club", "AwayScore": "1-14", "HomeTeam": "Na Gaeil Oga", "Venue": "St Catherines Park", "Competition": "Junior 1 Football Club Championship Group Three", "Status": "Result", "County": "Dublin", "AwayTeam": "Man O War", "CompetitionType": "Championship", "Time": "11:00", "Date": "15 Apr", "Path": "Club/Dublin//Championship", "Sport": ""}]}