{"Standings": [{"PointsDifference": 57, "Scored": 98, "Lost": 1, "Played": 5, "Team": "Clanna Gael-Fontenoy B", "Drew": 0, "Points": 8, "Won": 4, "Competition": "U13 Football Grading League Div.11", "Conceded": 41}, {"PointsDifference": 54, "Scored": 135, "Lost": 2, "Played": 5, "Team": "Craobh Chiarain", "Drew": 0, "Points": 6, "Won": 3, "Competition": "U13 Football Grading League Div.11", "Conceded": 81}, {"PointsDifference": 49, "Scored": 106, "Lost": 1, "Played": 5, "Team": "St Marks", "Drew": 0, "Points": 6, "Won": 3, "Competition": "U13 Football Grading League Div.11", "Conceded": 57}, {"PointsDifference": 8, "Scored": 93, "Lost": 2, "Played": 5, "Team": "Ballyboden St Endas C", "Drew": 0, "Points": 6, "Won": 3, "Competition": "U13 Football Grading League Div.11", "Conceded": 85}, {"PointsDifference": -45, "Scored": 49, "Lost": 3, "Played": 5, "Team": "St Judes B", "Drew": 0, "Points": 2, "Won": 1, "Competition": "U13 Football Grading League Div.11", "Conceded": 94}, {"PointsDifference": -123, "Scored": 61, "Lost": 5, "Played": 5, "Team": "Raheny B", "Drew": 0, "Points": 0, "Won": 0, "Competition": "U13 Football Grading League Div.11", "Conceded": 184}], "Fixtures": [], "Results": [{"Comment": null, "HomeScore": "5-9", "Referee": "TBC", "Grade": "Club", "AwayScore": "8-6", "HomeTeam": "Ballyboden St Endas C", "Venue": "St Colmcilles Community School", "Competition": "U13 Football Grading League Div.11", "Status": "Result", "County": "Dublin", "AwayTeam": "St Marks", "CompetitionType": "League", "Time": "10:30", "Date": "25 Mar", "Path": "Club/Dublin//League", "Sport": ""}, {"Comment": null, "HomeScore": "2-4", "Referee": "Chris McGinn Clontarf", "Grade": "Club", "AwayScore": "10-15", "HomeTeam": "Raheny B", "Venue": "St Annes 12A", "Competition": "U13 Football Grading League Div.11", "Status": "Result", "County": "Dublin", "AwayTeam": "Ballyboden St Endas C", "CompetitionType": "League", "Time": "13:30", "Date": "24 Mar", "Path": "Club/Dublin//League", "Sport": ""}, {"Comment": null, "HomeScore": "8-4", "Referee": "Adam Halpin - Thomas Davis", "Grade": "Club", "AwayScore": "2-6", "HomeTeam": "St Marks", "Venue": "McGee Park", "Competition": "U13 Football Grading League Div.11", "Status": "Result", "County": "Dublin", "AwayTeam": "Craobh Chiarain", "CompetitionType": "League", "Time": "13:30", "Date": "24 Mar", "Path": "Club/Dublin//League", "Sport": ""}, {"Comment": null, "HomeScore": "5-14", "Referee": "Brian Moore-Craobh Chiarain", "Grade": "Club", "AwayScore": "1-5", "HomeTeam": "Clanna Gael Fontenoy B", "Venue": "Sean Moore Park", "Competition": "U13 Football Grading League Div.11", "Status": "Result", "County": "Dublin", "AwayTeam": "St Judes B", "CompetitionType": "League", "Time": "13:30", "Date": "24 Mar", "Path": "Club/Dublin//League", "Sport": ""}, {"Comment": null, "HomeScore": "1-7", "Referee": "Sean Kellett - Whitehall Colmcille", "Grade": "Club", "AwayScore": "3-8", "HomeTeam": "Craobh Chiarain", "Venue": "Clonshaugh", "Competition": "U13 Football Grading League Div.11", "Status": "Result", "County": "Dublin", "AwayTeam": "Clanna Gael Fontenoy B", "CompetitionType": "League", "Time": "15:00", "Date": "10 Mar", "Path": "Club/Dublin//League", "Sport": ""}, {"Comment": null, "HomeScore": "2-6", "Referee": "Richard Sheil Nh. Olaf", "Grade": "Club", "AwayScore": "3-1", "HomeTeam": "St Judes B", "Venue": "Tymon Park", "Competition": "U13 Football Grading League Div.11", "Status": "Result", "County": "Dublin", "AwayTeam": "Raheny B", "CompetitionType": "League", "Time": "13:30", "Date": "10 Mar", "Path": "Club/Dublin//League", "Sport": ""}, {"Comment": null, "HomeScore": "W/O", "Referee": "Richard Sheil Nh. Olaf", "Grade": "Club", "AwayScore": "W/O", "HomeTeam": "Ballyboden St Endas C", "Venue": "St Colmcilles Community School", "Competition": "U13 Football Grading League Div.11", "Status": "Result", "County": "Dublin", "AwayTeam": "Clanna Gael Fontenoy B", "CompetitionType": "League", "Time": "14:30", "Date": "25 Feb", "Path": "Club/Dublin//League", "Sport": ""}, {"Comment": null, "HomeScore": "12-4", "Referee": "Ronnie Malone-St Marys", "Grade": "Club", "AwayScore": "0-5", "HomeTeam": "St Marks", "Venue": "McGee Park", "Competition": "U13 Football Grading League Div.11", "Status": "Result", "County": "Dublin", "AwayTeam": "Raheny B", "CompetitionType": "League", "Time": "14:30", "Date": "25 Feb", "Path": "Club/Dublin//League", "Sport": ""}, {"Comment": null, "HomeScore": "10-4", "Referee": "James Crehan - Raheny", "Grade": "Club", "AwayScore": "2-6", "HomeTeam": "Craobh Chiarain", "Venue": "St Annes 6", "Competition": "U13 Football Grading League Div.11", "Status": "Result", "County": "Dublin", "AwayTeam": "St Judes B", "CompetitionType": "League", "Time": "14:30", "Date": "25 Feb", "Path": "Club/Dublin//League", "Sport": ""}, {"Comment": null, "HomeScore": "0-3", "Referee": "Shane McDonnell - Stars of Erin", "Grade": "Club", "AwayScore": "7-7", "HomeTeam": "Ballyboden St Endas C", "Venue": "St Colmcilles Community School", "Competition": "U13 Football Grading League Div.11", "Status": "Result", "County": "Dublin", "AwayTeam": "Craobh Chiarain", "CompetitionType": "League", "Time": "15:00", "Date": "24 Feb", "Path": "Club/Dublin//League", "Sport": ""}, {"Comment": null, "HomeScore": "9-9", "Referee": "Kevin Donohoe-Naomh Fionnbarra", "Grade": "Club", "AwayScore": "3-6", "HomeTeam": "Clanna Gael Fontenoy B", "Venue": "Sean Moore Park", "Competition": "U13 Football Grading League Div.11", "Status": "Result", "County": "Dublin", "AwayTeam": "Raheny B", "CompetitionType": "League", "Time": "13:30", "Date": "24 Feb", "Path": "Club/Dublin//League", "Sport": ""}, {"Comment": null, "HomeScore": "", "Referee": "Jordan McKenna - Thomas Davis", "Grade": "Club", "AwayScore": "", "HomeTeam": "St Marks", "Venue": "McGee Park", "Competition": "U13 Football Grading League Div.11", "Status": "Result", "County": "Dublin", "AwayTeam": "St Judes B", "CompetitionType": "League", "Time": "13:30", "Date": "24 Feb", "Path": "Club/Dublin//League", "Sport": ""}, {"Comment": null, "HomeScore": "7-0", "Referee": "Barry Davis - Clontarf", "Grade": "Club", "AwayScore": "10-21", "HomeTeam": "Raheny B", "Venue": "St Annes 10", "Competition": "U13 Football Grading League Div.11", "Status": "Result", "County": "Dublin", "AwayTeam": "Craobh Chiarain", "CompetitionType": "League", "Time": "15:00", "Date": "17 Feb", "Path": "Club/Dublin//League", "Sport": ""}, {"Comment": null, "HomeScore": "4-5", "Referee": "Anthony Clinton-Croi Ro Naofa", "Grade": "Club", "AwayScore": "4-9", "HomeTeam": "St Judes B", "Venue": "Tymon Park", "Competition": "U13 Football Grading League Div.11", "Status": "Result", "County": "Dublin", "AwayTeam": "Ballyboden St Endas C", "CompetitionType": "League", "Time": "13:30", "Date": "17 Feb", "Path": "Club/Dublin//League", "Sport": ""}, {"Comment": null, "HomeScore": "4-4", "Referee": "Terry Carton  Naomh Fionnbarra", "Grade": "Club", "AwayScore": "2-2", "HomeTeam": "Clanna Gael Fontenoy B", "Venue": "Sean Moore Park", "Competition": "U13 Football Grading League Div.11", "Status": "Result", "County": "Dublin", "AwayTeam": "St Marks", "CompetitionType": "League", "Time": "13:30", "Date": "17 Feb", "Path": "Club/Dublin//League", "Sport": ""}]}