[{"ApiPath": "/Club/Kildare/Juvenile Football/Group/U14 Feile A Football Group 1", "Name": "U14 Feile A Football Group 1", "HasChildren": false}, {"ApiPath": "/Club/Kildare/Juvenile Football/Group/U14 Feile A Football Group 2", "Name": "U14 Feile A Football Group 2", "HasChildren": false}, {"ApiPath": "/Club/Kildare/Juvenile Football/Group/U14 Feile B Football Group 1", "Name": "U14 Feile B Football Group 1", "HasChildren": false}, {"ApiPath": "/Club/Kildare/Juvenile Football/Group/U14 Feile B Football Group 2", "Name": "U14 Feile B Football Group 2", "HasChildren": false}, {"ApiPath": "/Club/Kildare/Juvenile Football/Group/U14 Feile D Football Group 1", "Name": "U14 Feile D Football Group 1", "HasChildren": false}, {"ApiPath": "/Club/Kildare/Juvenile Football/Group/U14 Feile E Football Group 1", "Name": "U14 Feile E Football Group 1", "HasChildren": false}, {"ApiPath": "/Club/Kildare/Juvenile Football/Group/U14 Feile F Football Group 1", "Name": "U14 Feile F Football Group 1", "HasChildren": false}, {"ApiPath": "/Club/Kildare/Juvenile Football/Group/U14 Feile C Football Group 2", "Name": "U14 Feile C Football Group 2", "HasChildren": false}, {"ApiPath": "/Club/Kildare/Juvenile Football/Group/U14 Feile D Football Group 2", "Name": "U14 Feile D Football Group 2", "HasChildren": false}, {"ApiPath": "/Club/Kildare/Juvenile Football/Group/U14 Feile F Football Group 2", "Name": "U14 Feile F Football Group 2", "HasChildren": false}, {"ApiPath": "/Club/Kildare/Juvenile Football/Group/U14 Feile E Football Group 2", "Name": "U14 Feile E Football Group 2", "HasChildren": false}, {"ApiPath": "/Club/Kildare/Juvenile Football/Group/U14 Feile C Football Group 1", "Name": "U14 Feile C Football Group 1", "HasChildren": false}]