{"Standings": [], "Fixtures": [], "Results": [{"Comment": "Comment: \u00a0", "HomeScore": "", "Referee": "Referee: ", "Grade": "Club", "AwayScore": "", "HomeTeam": null, "Venue": "Venue:Dingle", "Competition": "Senior Football League Div 5 Gr B", "Status": "Result", "County": "Kerry", "AwayTeam": null, "CompetitionType": "League", "Time": "Time: 14:00", "Date": "01 Apr 2018", "Path": "Club/Kerry//League", "Sport": ""}, {"Comment": "Comment: \u00a0", "HomeScore": "", "Referee": "Referee: ", "Grade": "Club", "AwayScore": "", "HomeTeam": null, "Venue": "Venue:Bishop Moynihan/Tim Lenihan Park (Rathmore)", "Competition": "Senior Football League Div 5 Gr B", "Status": "Result", "County": "Kerry", "AwayTeam": null, "CompetitionType": "League", "Time": "Time: 14:00", "Date": "27 May 2018", "Path": "Club/Kerry//League", "Sport": ""}, {"Comment": "Comment: \u00a0", "HomeScore": "3-13", "Referee": "Referee: Tim Falvey", "Grade": "Club", "AwayScore": "4-6", "HomeTeam": "Dingle", "Venue": "Venue:Dingle", "Competition": "Senior Football League Div 5 Gr B", "Status": "Result", "County": "Kerry", "AwayTeam": "Tuosist", "CompetitionType": "League", "Time": "Time: 13:30", "Date": "17/06/2018 13:30", "Path": "Club/Kerry//League", "Sport": ""}, {"Comment": "Comment: \u00a0", "HomeScore": "4-4", "Referee": "Referee: Christy Crowley", "Grade": "Club", "AwayScore": "4-11", "HomeTeam": "Rathmore", "Venue": "Venue:Bishop Moynihan/Tim Lenihan Park (Rathmore)", "Competition": "Senior Football League Div 5 Gr B", "Status": "Result", "County": "Kerry", "AwayTeam": "Duagh", "CompetitionType": "League", "Time": "Time: 19:00", "Date": "16/06/2018 19:00", "Path": "Club/Kerry//League", "Sport": ""}, {"Comment": "Comment: \u00a0", "HomeScore": "0-9", "Referee": "Referee: Gerard Murphy", "Grade": "Club", "AwayScore": "0-12", "HomeTeam": "Sneem/Derrynane", "Venue": "Venue:Derrynane", "Competition": "Senior Football League Div 5 Gr B", "Status": "Result", "County": "Kerry", "AwayTeam": "Moyvane", "CompetitionType": "League", "Time": "Time: 18:30", "Date": "16/06/2018 18:30", "Path": "Club/Kerry//League", "Sport": ""}, {"Comment": "Comment: \u00a0", "HomeScore": "1-10", "Referee": "Referee: Patrick Sheehy", "Grade": "Club", "AwayScore": "1-9", "HomeTeam": "Tuosist", "Venue": "Venue:Tousist", "Competition": "Senior Football League Div 5 Gr B", "Status": "Result", "County": "Kerry", "AwayTeam": "Sneem/Derrynane", "CompetitionType": "League", "Time": "Time: 14:00", "Date": "10/06/2018 14:00", "Path": "Club/Kerry//League", "Sport": ""}, {"Comment": "Comment: \u00a0", "HomeScore": "1-13", "Referee": "Referee: Dan Hayes", "Grade": "Club", "AwayScore": "2-12", "HomeTeam": "Ballyduff", "Venue": "Venue:Ballyduff", "Competition": "Senior Football League Div 5 Gr B", "Status": "Result", "County": "Kerry", "AwayTeam": "Rathmore", "CompetitionType": "League", "Time": "Time: 19:30", "Date": "09/06/2018 19:30", "Path": "Club/Kerry//League", "Sport": ""}, {"Comment": "Comment:  conceded by dingle ", "HomeScore": "", "Referee": "Referee: Michael Joy", "Grade": "Club", "AwayScore": "", "HomeTeam": "Duagh", "Venue": "Venue:Duagh", "Competition": "Senior Football League Div 5 Gr B", "Status": "Result", "County": "Kerry", "AwayTeam": "Dingle", "CompetitionType": "League", "Time": "Time: 19:30", "Date": "09/06/2018 19:30", "Path": "Club/Kerry//League", "Sport": ""}, {"Comment": "Comment:  conceded by tuosist ", "HomeScore": "", "Referee": "Referee: Diarmuid O Carroll", "Grade": "Club", "AwayScore": "", "HomeTeam": "Moyvane", "Venue": "Venue:Moyvane", "Competition": "Senior Football League Div 5 Gr B", "Status": "Result", "County": "Kerry", "AwayTeam": "Tuosist", "CompetitionType": "League", "Time": "Time: 14:00", "Date": "27/05/2018 14:00", "Path": "Club/Kerry//League", "Sport": ""}, {"Comment": "Comment: \u00a0", "HomeScore": "0-8", "Referee": "Referee: Maurice Murphy", "Grade": "Club", "AwayScore": "1-12", "HomeTeam": "Sneem/Derrynane", "Venue": "Venue:Derrynane", "Competition": "Senior Football League Div 5 Gr B", "Status": "Result", "County": "Kerry", "AwayTeam": "Duagh", "CompetitionType": "League", "Time": "Time: 14:00", "Date": "27/05/2018 14:00", "Path": "Club/Kerry//League", "Sport": ""}, {"Comment": "Comment: \u00a0", "HomeScore": "1-11", "Referee": "Referee: Tim Brosnan", "Grade": "Club", "AwayScore": "0-15", "HomeTeam": "Dingle", "Venue": "Venue:Dingle", "Competition": "Senior Football League Div 5 Gr B", "Status": "Result", "County": "Kerry", "AwayTeam": "Ballyduff", "CompetitionType": "League", "Time": "Time: 17:00", "Date": "26/05/2018 17:00", "Path": "Club/Kerry//League", "Sport": ""}, {"Comment": "Comment: \u00a0", "HomeScore": "6-16", "Referee": "Referee: Tom Mc Carthy", "Grade": "Club", "AwayScore": "1-14", "HomeTeam": "Rathmore", "Venue": "Venue:Bishop Moynihan/Tim Lenihan Park (Rathmore)", "Competition": "Senior Football League Div 5 Gr B", "Status": "Result", "County": "Kerry", "AwayTeam": "Dingle", "CompetitionType": "League", "Time": "Time: 15:15", "Date": "13/05/2018 15:15", "Path": "Club/Kerry//League", "Sport": ""}, {"Comment": "Comment: \u00a0", "HomeScore": "2-15", "Referee": "Referee: Denny F O Sullivan", "Grade": "Club", "AwayScore": "0-7", "HomeTeam": "Ballyduff", "Venue": "Venue:Ballyduff", "Competition": "Senior Football League Div 5 Gr B", "Status": "Result", "County": "Kerry", "AwayTeam": "Sneem/Derrynane", "CompetitionType": "League", "Time": "Time: 19:00", "Date": "12/05/2018 19:00", "Path": "Club/Kerry//League", "Sport": ""}, {"Comment": "Comment: \u00a0", "HomeScore": "4-16", "Referee": "Referee: Eddie Barrett", "Grade": "Club", "AwayScore": "0-7", "HomeTeam": "Duagh", "Venue": "Venue:Duagh", "Competition": "Senior Football League Div 5 Gr B", "Status": "Result", "County": "Kerry", "AwayTeam": "Moyvane", "CompetitionType": "League", "Time": "Time: 19:00", "Date": "12/05/2018 19:00", "Path": "Club/Kerry//League", "Sport": ""}, {"Comment": "Comment: \u00a0", "HomeScore": "0-6", "Referee": "Referee: Gerard O Carroll", "Grade": "Club", "AwayScore": "0-9", "HomeTeam": "Moyvane", "Venue": "Venue:Moyvane", "Competition": "Senior Football League Div 5 Gr B", "Status": "Result", "County": "Kerry", "AwayTeam": "Ballyduff", "CompetitionType": "League", "Time": "Time: 19:00", "Date": "05/05/2018 19:00", "Path": "Club/Kerry//League", "Sport": ""}, {"Comment": "Comment: \u00a0", "HomeScore": "2-11", "Referee": "Referee: James O Connor", "Grade": "Club", "AwayScore": "1-11", "HomeTeam": "Sneem/Derrynane", "Venue": "Venue:Sneem", "Competition": "Senior Football League Div 5 Gr B", "Status": "Result", "County": "Kerry", "AwayTeam": "Rathmore", "CompetitionType": "League", "Time": "Time: 14:00", "Date": "22/04/2018 14:00", "Path": "Club/Kerry//League", "Sport": ""}, {"Comment": "Comment: \u00a0", "HomeScore": "1-8", "Referee": "Referee: Paudie B Randles", "Grade": "Club", "AwayScore": "2-16", "HomeTeam": "Tuosist", "Venue": "Venue:Tousist", "Competition": "Senior Football League Div 5 Gr B", "Status": "Result", "County": "Kerry", "AwayTeam": "Duagh", "CompetitionType": "League", "Time": "Time: 14:00", "Date": "22/04/2018 14:00", "Path": "Club/Kerry//League", "Sport": ""}, {"Comment": "Comment: \u00a0", "HomeScore": "3-15", "Referee": "Referee: Dan Hayes", "Grade": "Club", "AwayScore": "2-6", "HomeTeam": "Ballyduff", "Venue": "Venue:Ballyduff", "Competition": "Senior Football League Div 5 Gr B", "Status": "Result", "County": "Kerry", "AwayTeam": "Tuosist", "CompetitionType": "League", "Time": "Time: 14:30", "Date": "25/03/2018 14:30", "Path": "Club/Kerry//League", "Sport": ""}, {"Comment": "Comment: \u00a0", "HomeScore": "0-14", "Referee": "Referee: ", "Grade": "Club", "AwayScore": "3-17", "HomeTeam": "Dingle", "Venue": "Venue:Dingle", "Competition": "Senior Football League Div 5 Gr B", "Status": "Result", "County": "Kerry", "AwayTeam": "Sneem/Derrynane", "CompetitionType": "League", "Time": "Time: 14:00", "Date": "25/03/2018 14:00", "Path": "Club/Kerry//League", "Sport": ""}, {"Comment": "Comment: \u00a0", "HomeScore": "0-8", "Referee": "Referee: Jimmy O Shea", "Grade": "Club", "AwayScore": "3-15", "HomeTeam": "Rathmore", "Venue": "Venue:Bishop Moynihan/Tim Lenihan Park (Rathmore)", "Competition": "Senior Football League Div 5 Gr B", "Status": "Result", "County": "Kerry", "AwayTeam": "Moyvane", "CompetitionType": "League", "Time": "Time: 13:30", "Date": "25/03/2018 13:30", "Path": "Club/Kerry//League", "Sport": ""}, {"Comment": "Comment: \u00a0", "HomeScore": "2-12", "Referee": "Referee: Michael Joy", "Grade": "Club", "AwayScore": "1-11", "HomeTeam": "Moyvane", "Venue": "Venue:Moyvane", "Competition": "Senior Football League Div 5 Gr B", "Status": "Result", "County": "Kerry", "AwayTeam": "Dingle", "CompetitionType": "League", "Time": "Time: 14:00", "Date": "11/03/2018 14:00", "Path": "Club/Kerry//League", "Sport": ""}, {"Comment": "Comment: \u00a0", "HomeScore": "0-17", "Referee": "Referee: Tim Brosnan", "Grade": "Club", "AwayScore": "1-11", "HomeTeam": "Duagh", "Venue": "Venue:Duagh", "Competition": "Senior Football League Div 5 Gr B", "Status": "Result", "County": "Kerry", "AwayTeam": "Ballyduff", "CompetitionType": "League", "Time": "Time: 13:00", "Date": "11/03/2018 13:00", "Path": "Club/Kerry//League", "Sport": ""}, {"Comment": "Comment: \u00a0", "HomeScore": "1-19", "Referee": "Referee: ", "Grade": "Club", "AwayScore": "1-9", "HomeTeam": "Tuosist", "Venue": "Venue:Tousist", "Competition": "Senior Football League Div 5 Gr B", "Status": "Result", "County": "Kerry", "AwayTeam": "Rathmore", "CompetitionType": "League", "Time": "Time: 12:30", "Date": "11/03/2018 12:30", "Path": "Club/Kerry//League", "Sport": ""}]}