{"Standings": [], "Fixtures": [], "Results": [{"Comment": null, "HomeScore": "", "Referee": "Joe Murray", "Grade": "Club", "AwayScore": "", "HomeTeam": "Round Towers Lusk", "Venue": "St Margarets", "Competition": "Junior 4 All County Football Championship", "Status": "Result", "County": "Dublin", "AwayTeam": "Kilmacud Crokes", "CompetitionType": "Championship", "Time": "14:00", "Date": "28 Oct", "Path": "Club/Dublin//Championship", "Sport": ""}, {"Comment": null, "HomeScore": "3-8", "Referee": "Joe Murray", "Grade": "Club", "AwayScore": "2-7", "HomeTeam": "Round Towers Lusk", "Venue": "St Margarets", "Competition": "Junior 4 All County Football Championship", "Status": "Result", "County": "Dublin", "AwayTeam": "Raheny", "CompetitionType": "Championship", "Time": "14:00", "Date": "28 Oct", "Path": "Club/Dublin//Championship", "Sport": ""}]}